genomicsurveillance/__init__.py
genomicsurveillance/config.py
genomicsurveillance/data/__init__.py
genomicsurveillance/data/aliases.txt
genomicsurveillance/data/api.py
genomicsurveillance/data/geo_data.py
genomicsurveillance/data/gov_uk.py
genomicsurveillance/data/meta_data.py
genomicsurveillance/data/uk.geojson
genomicsurveillance/data/uk_meta.csv
genomicsurveillance/distributions.py
genomicsurveillance/handler.py
genomicsurveillance/models/__init__.py
genomicsurveillance/models/base.py
genomicsurveillance/models/clock_reset.py
genomicsurveillance/models/legacy.py
genomicsurveillance/models/sites.py
genomicsurveillance/plots/__init__.py
genomicsurveillance/plots/basic.py
genomicsurveillance/plots/england.py
genomicsurveillance/types.py
genomicsurveillance/utils/__init__.py
genomicsurveillance/utils/epiestim.py
genomicsurveillance/utils/helper.py
genomicsurveillance/utils/knots.py
genomicsurveillance/utils/lineages.py
genomicsurveillance-0.5.3.dist-info/LICENSE
genomicsurveillance-0.5.3.dist-info/WHEEL
genomicsurveillance-0.5.3.dist-info/METADATA
genomicsurveillance-0.5.3.dist-info/RECORD
