Metadata-Version: 2.1
Name: genomicsurveillance
Version: 0.5.3
Summary: 
Author: Harald Vohringer
Author-email: harald.voeh@gmail.com
Requires-Python: >=3.7.1,<4.0.0
Classifier: Programming Language :: Python :: 3
Classifier: Programming Language :: Python :: 3.8
Classifier: Programming Language :: Python :: 3.9
Provides-Extra: docs
Provides-Extra: geopandas
Provides-Extra: matplotlib
Provides-Extra: uk-covid19
Requires-Dist: geopandas (>=0.9.0,<0.10.0); extra == "geopandas"
Requires-Dist: matplotlib (>=3.3.4,<4.0.0); extra == "matplotlib"
Requires-Dist: numpyro (==0.6.0)
Requires-Dist: pandas (>=1.1.0,<2.0.0)
Requires-Dist: sphinx (>=3,<4); extra == "docs"
Requires-Dist: uk-covid19 (>=1.2.0,<2.0.0); extra == "uk-covid19"
